{
	"schemaVersion": "0.1.0",
	"name": "Wikipedia",
	"behavior": "create",
	"noteContentFormat": "{{selectorHtml:#mw-content-text|remove_html:(\".navbox,.printfooter,.side-box\")|markdown}}",
	"properties": [
		{
			"name": "title",
			"value": "{{title}}",
			"type": "text"
		},
		{
			"name": "source",
			"value": "{{url}}",
			"type": "text"
		},
		{
			"name": "author",
			"value": "Wikipedia",
			"type": "text"
		},
		{
			"name": "created",
			"value": "{{date}}",
			"type": "date"
		},
		{
			"name": "description",
			"value": "{{description}}",
			"type": "text"
		},
		{
			"name": "tags",
			"value": "clippings",
			"type": "multitext"
		},
		{
			"name": "image",
			"value": "{{image}}",
			"type": "text"
		}
	],
	"triggers": [
		"/^https:\\/\\/[a-z]{2,3}\\.wikipedia\\.org\\/wiki\\/?$/"
	],
	"noteNameFormat": "{{title}}",
	"path": "Clippings"
}
